{"data":{"_id":8000,"properties":{"id":{"name":"id","kind":"scalar","primary":true,"type":"string","runtimeType":"string","array":false},"bank":{"name":"bank","kind":"m:1","cascade":["persist"],"owner":true,"createForeignKeyConstraint":true,"type":"Bank","array":false,"runtimeType":"Bank"},"amount":{"name":"amount","kind":"scalar","type":"decimal","getter":false,"setter":false,"array":false,"runtimeType":"number"},"type":{"name":"type","kind":"scalar","enum":true,"items":["INFLOW","OUTFLOW","NOTE"],"type":"BankTransactionType","array":false,"runtimeType":"BankTransactionType"},"description":{"name":"description","kind":"scalar","type":"text","nullable":true,"getter":false,"setter":false,"array":false,"optional":true,"runtimeType":"string"},"reference":{"name":"reference","kind":"scalar","nullable":true,"getter":false,"setter":false,"type":"string","array":false,"optional":true,"runtimeType":"string"},"createdBy":{"name":"createdBy","kind":"m:1","cascade":["persist"],"owner":true,"createForeignKeyConstraint":true,"type":"User","array":false,"runtimeType":"User"},"createdAt":{"name":"createdAt","kind":"scalar","getter":false,"setter":false,"type":"Date","runtimeType":"Date","array":false}},"primaryKeys":["id"],"filters":{},"hooks":{},"indexes":[{"properties":"createdAt"}],"uniques":[],"className":"BankTransaction","path":"./src/entities/BankTransaction.ts","collection":"bank_transactions","name":"BankTransaction","abstract":false,"internal":true,"constructorParams":[],"toJsonParams":[],"useCache":true,"compositePK":false,"simplePK":true},"origin":"./src/entities/BankTransaction.ts","hash":"c48b3c3152c3bfc3a796dc52d764bdb6","version":"6.5.9"}
